<?xml version="1.0" encoding="utf-8"?>
<annotation>
<folder>images</folder>
<filename>1259e293-20221216-145452.jpg</filename>
<source>
<database>MyDatabase</database>
<annotation>COCO2017</annotation>
<image>flickr</image>
<flickrid>NULL</flickrid>
<annotator>3</annotator>
</source>
<owner>
<flickrid>NULL</flickrid>
<name>Label Studio</name>
</owner>
<size>
<width>640</width>
<height>480</height>
<depth>3</depth>
</size>
<segmented>0</segmented>
<object>
<name>Crosswalk</name>
<pose>Unspecified</pose>
<truncated>0</truncated>
<difficult>0</difficult>
<bndbox>
<xmin>548</xmin>
<ymin>126</ymin>
<xmax>622</xmax>
<ymax>190</ymax>
</bndbox>
</object>
<object>
<name>Parking</name>
<pose>Unspecified</pose>
<truncated>0</truncated>
<difficult>0</difficult>
<bndbox>
<xmin>387</xmin>
<ymin>100</ymin>
<xmax>401</xmax>
<ymax>117</ymax>
</bndbox>
</object>
<object>
<name>Pedestrian</name>
<pose>Unspecified</pose>
<truncated>0</truncated>
<difficult>0</difficult>
<bndbox>
<xmin>270</xmin>
<ymin>148</ymin>
<xmax>349</xmax>
<ymax>244</ymax>
</bndbox>
</object>
</annotation>
